INSTALL
LICENSE
README
setup.py
src/pypatterns/__init__.py
src/pypatterns.egg-info/PKG-INFO
src/pypatterns.egg-info/SOURCES.txt
src/pypatterns.egg-info/dependency_links.txt
src/pypatterns.egg-info/requires.txt
src/pypatterns.egg-info/top_level.txt
src/pypatterns/command/__init__.py
src/pypatterns/filter/__init__.py
src/pypatterns/relational/__init__.py
src/pypatterns/relational/commands.py
test/TestAccumulator.py
test/TestCommand.py
test/TestFilter.py
test/TestRelational.py
test/TestRelationalCommand.py
test/TestRelationalPickle.py
test/__init__.py