Metadata-Version: 1.0
Name: pypatterns
Version: 0.1.4
Summary: generic patterns
Home-page: http://code.google.com/p/pypatterns/
Author: michael j pan
Author-email: mikepan@gmail.com
License: New BSD
Keywords: object relational command filter
Platform: All
